{
  "data": [
    {
      "id": 1,
      "name": "Amir"
    },
    {
      "id": 2,
      "name": "Moein"
    },
    {
      "id": 3,
      "name": "Hesam"
    },
    {
      "id": 4,
      "name": "Ali"
    },
    {
      "id": 5,
      "name": "Hosein"
    },
    {
      "id": 6,
      "name": "Shahryar"
    },
    {
      "id": 7,
      "name": "Farid"
    },
    {
      "id": 8,
      "name": "Sina"
    },
    {
      "id": 9,
      "name": "Raha"
    },
    {
      "id": 10,
      "name": "Zahra"
    }
  ]
}